edge_ai_cnn_accelerator/rtl/riscv_core_controller.v
`timescale 1ns / 1ps

module riscv_core_controller (
    input wire clk,
    input wire rst_n,
    
    // Simple Memory-mapped IO bus to configure CNN
    output reg [31:0] mem_addr,
    output reg [31:0] mem_wdata,
    output reg mem_wen,
    output reg mem_ren,
    input wire [31:0] mem_rdata,
    input wire mem_ready
);

    // This module acts as a simplified RISC-V executing a predefined sequence
    // simulating firmware loading weights, configuring, and starting CNN.
    
    reg [3:0] state;
    
    localparam INIT_MEM  = 4'd0;
    localparam CONF_W    = 4'd1;
    localparam CONF_H    = 4'd2;
    localparam CONF_C    = 4'd3;
    localparam START     = 4'd4;
    localparam POLL      = 4'd5;
    localparam FINISH    = 4'd6;

    always @(posedge clk or negedge rst_n) begin
        if (!rst_n) begin
            state <= INIT_MEM;
            mem_addr <= 0;
            mem_wdata <= 0;
            mem_wen <= 0;
            mem_ren <= 0;
        end else begin
            mem_wen <= 0;
            mem_ren <= 0;
            case (state)
                INIT_MEM: begin
                    // Firmware delay/init
                    state <= CONF_W;
                end
                CONF_W: begin
                    mem_addr <= 32'h10;
                    mem_wdata <= 32'h08; // width 8
                    mem_wen <= 1;
                    if (mem_ready) state <= CONF_H;
                end
                CONF_H: begin
                    mem_addr <= 32'h14;
                    mem_wdata <= 32'h08; // height 8
                    mem_wen <= 1;
                    if (mem_ready) state <= CONF_C;
                end
                CONF_C: begin
                    mem_addr <= 32'h18;
                    mem_wdata <= 32'h03; // channels 3
                    mem_wen <= 1;
                    if (mem_ready) state <= START;
                end
                START: begin
                    mem_addr <= 32'h00;
                    mem_wdata <= 32'h01; // START conv1
                    mem_wen <= 1;
                    if (mem_ready) state <= POLL;
                end
                POLL: begin
                    mem_addr <= 32'h00;
                    mem_ren <= 1;
                    if (mem_ready) begin
                        if (mem_rdata[1] == 1'b1) // DONE bit set
                            state <= FINISH;
                    end
                end
                FINISH: begin
                    // Execution done
                end
                default: begin
                    state <= INIT_MEM;
                end
            endcase
        end
    end

    // Suppress unused-signal warnings for mem_rdata bits not checked
    wire _unused = &{1'b0, mem_rdata[31:2], mem_rdata[0], 1'b0};

endmodule

edge_ai_cnn_accelerator/tb/riscv_control_tb.v
`timescale 1ns / 1ps

module riscv_control_tb;

    reg clk, rst_n;
    wire [31:0] mem_addr, mem_wdata;
    wire mem_wen, mem_ren;
    wire [31:0] mem_rdata;
    reg mem_ready;

    // Instance of RISC-V controller
    riscv_core_controller uut (
        .clk(clk),
        .rst_n(rst_n),
        .mem_addr(mem_addr),
        .mem_wdata(mem_wdata),
        .mem_wen(mem_wen),
        .mem_ren(mem_ren),
        .mem_rdata(mem_rdata),
        .mem_ready(mem_ready)
    );

    always #5 clk = ~clk;

    // Simulate simple memory response
    always @(posedge clk) begin
        if (mem_wen || mem_ren) begin
            // Ready in next cycle
            mem_ready <= 1'b1;
        end else begin
            mem_ready <= 1'b0;
        end
    end

    // Assign mock read data if asking for status
    assign mem_rdata = (mem_addr == 32'h00) ? 32'h02 : 32'h00; // Mock DONE bit = 1

    initial begin
        $dumpfile("riscv_control_tb.vcd");
        $dumpvars(0, riscv_control_tb);
        
        clk = 0;
        rst_n = 0;
        mem_ready = 0;
        
        #20 rst_n = 1;

        // Monitor writes
        $monitor("Time: %0t | ADDR: %h | WDATA: %h | WEN: %b | REN: %b",
                 $time, mem_addr, mem_wdata, mem_wen, mem_ren);
        
        // Allow enough time for the state machine to reach FINISH
        #200;
        $finish;
    end
endmodule

edge_ai_cnn_accelerator/riscv_control_tb.vcd
$date
	Sun Mar 15 16:48:02 2026
$end
$version
	Icarus Verilog
$end
$timescale
	1ps
$end
$scope module riscv_control_tb $end
$var wire 1 ! mem_wen $end
$var wire 32 " mem_wdata [31:0] $end
$var wire 1 # mem_ren $end
$var wire 32 $ mem_rdata [31:0] $end
$var wire 32 % mem_addr [31:0] $end
$var reg 1 & clk $end
$var reg 1 ' mem_ready $end
$var reg 1 ( rst_n $end
$scope module uut $end
$var wire 1 & clk $end
$var wire 32 ) mem_rdata [31:0] $end
$var wire 1 ' mem_ready $end
$var wire 1 ( rst_n $end
$var wire 1 * _unused $end
$var parameter 4 + CONF_C $end
$var parameter 4 , CONF_H $end
$var parameter 4 - CONF_W $end
$var parameter 4 . FINISH $end
$var parameter 4 / INIT_MEM $end
$var parameter 4 0 POLL $end
$var parameter 4 1 START $end
$var reg 32 2 mem_addr [31:0] $end
$var reg 1 # mem_ren $end
$var reg 32 3 mem_wdata [31:0] $end
$var reg 1 ! mem_wen $end
$var reg 4 4 state [3:0] $end
$upscope $end
$upscope $end
$enddefinitions $end
$comment Show the parameter values. $end
$dumpall
b100 1
b101 0
b0 /
b110 .
b1 -
b10 ,
b11 +
$end
#0
$dumpvars
b0 4
b0 3
b0 2
0*
b10 )
0(
0'
0&
b0 %
b10 $
0#
b0 "
0!
$end
#5000
1&
#10000
0&
#15000
1&
#20000
0&
1(
#25000
b1 4
1&
#30000
0&
#35000
b0 $
b0 )
1!
b1000 "
b1000 3
b10000 %
b10000 2
1&
#40000
0&
#45000
1!
1'
1&
#50000
0&
#55000
b10 4
1!
1&
#60000
0&
#65000
b11 4
b10100 %
b10100 2
1!
1&
#70000
0&
#75000
b100 4
b11 "
b11 3
b11000 %
b11000 2
1!
1&
#80000
0&
#85000
b10 $
b10 )
b101 4
b1 "
b1 3
b0 %
b0 2
1!
1&
#90000
0&
#95000
b110 4
1#
0!
1&
#100000
0&
#105000
0#
1&
#110000
0&
#115000
0'
1&
