edge_ai_cnn_accelerator/rtl/sliding_window.v
`timescale 1ns / 1ps

module sliding_window #(
    parameter DATA_WIDTH = 8
)(
    input wire clk,
    input wire rst_n,
    input wire en,
    
    // In from line buffers
    input wire [DATA_WIDTH-1:0] col_row0, // Bottom row
    input wire [DATA_WIDTH-1:0] col_row1, // Middle row
    input wire [DATA_WIDTH-1:0] col_row2, // Top row
    
    // Output 9 pixels of the 3x3 window
    // [0-2]: Top row (left to right)
    // [3-5]: Mid row
    // [6-8]: Bot row
    output reg [DATA_WIDTH*9-1:0] window_out,
    output reg valid_out
);

    // Shift registers for the window
    reg [DATA_WIDTH-1:0] r0_c0, r0_c1, r0_c2; // Top row
    reg [DATA_WIDTH-1:0] r1_c0, r1_c1, r1_c2; // Middle row
    reg [DATA_WIDTH-1:0] r2_c0, r2_c1, r2_c2; // Bottom row

    always @(posedge clk or negedge rst_n) begin
        if (!rst_n) begin
            r0_c0 <= 0; r0_c1 <= 0; r0_c2 <= 0;
            r1_c0 <= 0; r1_c1 <= 0; r1_c2 <= 0;
            r2_c0 <= 0; r2_c1 <= 0; r2_c2 <= 0;
            window_out <= 0;
            valid_out <= 0;
        end else if (en) begin
            // Shift values right
            r0_c0 <= r0_c1; r0_c1 <= r0_c2; r0_c2 <= col_row2;
            r1_c0 <= r1_c1; r1_c1 <= r1_c2; r1_c2 <= col_row1;
            r2_c0 <= r2_c1; r2_c1 <= r2_c2; r2_c2 <= col_row0;
            
            // Map to flat output vector
            // Format: {bot_R, bot_M, bot_L, mid_R, mid_M, mid_L, top_R, top_M, top_L}
            // For MAC alignment:
            // window_out[8*8 +: 8] = top_left
            // window_out[0*8 +: 8] = bottom_right
            
            window_out <= {
                col_row0, r2_c2, r2_c0, // Bottom row: right, mid, left
                col_row1, r1_c2, r1_c0, // Middle row: right, mid, left
                col_row2, r0_c2, r0_c0  // Top row: right, mid, left
            };
            valid_out <= 1'b1;
        end else begin
            valid_out <= 1'b0;
        end
    end

endmodule

edge_ai_cnn_accelerator/tb/sliding_window_tb.v
`timescale 1ns / 1ps

module sliding_window_tb;

    reg clk;
    reg rst_n;
    reg en;
    reg [7:0] col_row0; // Bottom row
    reg [7:0] col_row1; // Middle row
    reg [7:0] col_row2; // Top row
    
    wire [71:0] window_out;
    wire valid_out;

    sliding_window uut (
        .clk(clk),
        .rst_n(rst_n),
        .en(en),
        .col_row0(col_row0),
        .col_row1(col_row1),
        .col_row2(col_row2),
        .window_out(window_out),
        .valid_out(valid_out)
    );

    parameter DEBUG_LEVEL = 1;

    always #5 clk = ~clk;

    initial begin
        // Configurable Waveform Dumping
        if (DEBUG_LEVEL > 0) begin
            $dumpfile("sim_out/waveforms/sliding_window.fst");
            if (DEBUG_LEVEL == 1)      $dumpvars(1, sliding_window_tb); // Top-level only
            else if (DEBUG_LEVEL == 2) $dumpvars(0, sliding_window_tb.uut); // Accelerator/uut only
            else                       $dumpvars(0, sliding_window_tb); // Full debug dump
        end
        
        clk = 0;
        rst_n = 0;
        en = 0;
        col_row0 = 0;
        col_row1 = 0;
        col_row2 = 0;
        
        #20 rst_n = 1;
        
        // Cycle 1
        #10;
        en = 1;
        col_row2 = 8'h11; // Top
        col_row1 = 8'h21; // Mid
        col_row0 = 8'h31; // Bot
        
        // Cycle 2
        #10;
        col_row2 = 8'h12;
        col_row1 = 8'h22;
        col_row0 = 8'h32;
        
        // Cycle 3 (Window should be full after this cycle)
        #10;
        col_row2 = 8'h13;
        col_row1 = 8'h23;
        col_row0 = 8'h33;
        
        // Delay to allow outputs to register
        #5; 
        
        // Expected output layout mapping check
        if (valid_out) begin
            $display("Window Valid!");
            $display("Top Row: %x %x %x", window_out[23:16], window_out[15:8], window_out[7:0]);
            $display("Mid Row: %x %x %x", window_out[47:40], window_out[39:32], window_out[31:24]);
            $display("Bot Row: %x %x %x", window_out[71:64], window_out[63:56], window_out[55:48]);
            $display("SW Test PASS");
        end else begin
            $display("FAIL: Valid signal not asserted");
        end

        #5 en = 0;
        
        #30 $finish;
    end

endmodule

edge_ai_cnn_accelerator/sliding_window_tb.vcd
$date
	Sat Mar 14 13:49:29 2026
$end
$version
	Icarus Verilog
$end
$timescale
	1ps
$end
$scope module sliding_window_tb $end
$var wire 72 ! window_out [71:0] $end
$var wire 1 " valid_out $end
$var reg 1 # clk $end
$var reg 8 $ col_row0 [7:0] $end
$var reg 8 % col_row1 [7:0] $end
$var reg 8 & col_row2 [7:0] $end
$var reg 1 ' en $end
$var reg 1 ( rst_n $end
$scope module uut $end
$var wire 1 # clk $end
$var wire 8 ) col_row0 [7:0] $end
$var wire 8 * col_row1 [7:0] $end
$var wire 8 + col_row2 [7:0] $end
$var wire 1 ' en $end
$var wire 1 ( rst_n $end
$var parameter 32 , DATA_WIDTH $end
$var reg 8 - r0_c0 [7:0] $end
$var reg 8 . r0_c1 [7:0] $end
$var reg 8 / r0_c2 [7:0] $end
$var reg 8 0 r1_c0 [7:0] $end
$var reg 8 1 r1_c1 [7:0] $end
$var reg 8 2 r1_c2 [7:0] $end
$var reg 8 3 r2_c0 [7:0] $end
$var reg 8 4 r2_c1 [7:0] $end
$var reg 8 5 r2_c2 [7:0] $end
$var reg 1 " valid_out $end
$var reg 72 6 window_out [71:0] $end
$upscope $end
$upscope $end
$enddefinitions $end
$comment Show the parameter values. $end
$dumpall
b1000 ,
$end
#0
$dumpvars
b0 6
b0 5
b0 4
b0 3
b0 2
b0 1
b0 0
b0 /
b0 .
b0 -
b0 +
b0 *
b0 )
0(
0'
b0 &
b0 %
b0 $
0#
0"
b0 !
$end
#5000
1#
#10000
0#
#15000
1#
#20000
0#
1(
#25000
1#
#30000
0#
b110001 $
b110001 )
b100001 %
b100001 *
b10001 &
b10001 +
1'
#35000
1"
b1100010000000000000000001000010000000000000000000100010000000000000000 !
b1100010000000000000000001000010000000000000000000100010000000000000000 6
b110001 5
b100001 2
b10001 /
1#
#40000
0#
b110010 $
b110010 )
b100010 %
b100010 *
b10010 &
b10010 +
#45000
b1100100011000100000000001000100010000100000000000100100001000100000000 !
b1100100011000100000000001000100010000100000000000100100001000100000000 6
b110010 5
b110001 4
b100010 2
b100001 1
b10010 /
b10001 .
1#
#50000
0#
b110011 $
b110011 )
b100011 %
b100011 *
b10011 &
b10011 +
#55000
b1100110011001000110001001000110010001000100001000100110001001000010001 !
b1100110011001000110001001000110010001000100001000100110001001000010001 6
b110011 5
b110010 4
b110001 3
b100011 2
b100010 1
b100001 0
b10011 /
b10010 .
b10001 -
1#
#60000
0#
0'
#65000
0"
1#
